{"1604910603396":[{"title":"TypeScript学习笔记","time":"2020年11月05日 » "},{"title":"计算机组成原理","time":"2020年11月02日 » "},{"title":"React学习记录","time":"2020年11月01日 » "},{"title":"使用自定义过滤器的方式实现 Spring Security 的 CORS 跨域配置","time":"2020年10月18日 » "},{"title":"微信小程序云开发登录流程","time":"2020年10月15日 » "},{"title":"微信小程序的userInfoReadyCallback相关解释","time":"2020年10月15日 » "},{"title":"大前端学习路线（详解）","time":"2020年10月13日 » "},{"title":"JavaScript进阶【1-5】JavaScript深入之4类常见内存泄漏及如何避免","time":"2020年10月13日 » "},{"title":"JavaScript进阶【1-4】JavaScript深入之带你走进内存机制","time":"2020年10月13日 » "},{"title":"JavaScript进阶【1-3】JavaScript深入之内存空间详细图解","time":"2020年10月13日 » "},{"title":"配置.editorconfig文件统一开发风格","time":"2020年10月13日 » "},{"title":"ES6处理异步问题的方法：async和await","time":"2020年10月13日 » "},{"title":"通过JavaScript实现设备尺寸的自适应","time":"2020年10月13日 » "},{"title":"JavaScript进阶【1-2】JavaScript深入之执行上下文栈和变量对象","time":"2020年10月13日 » "},{"title":"JavaScript进阶【1-1】理解JavaScript 中的执行上下文和执行栈","time":"2020年10月13日 » "},{"title":">>点击查看更多文章...","time":""}],"1604910619005":[{"title":"TypeScript学习笔记","time":"2020年11月05日 » "},{"title":"计算机组成原理","time":"2020年11月02日 » "},{"title":"React学习记录","time":"2020年11月01日 » "},{"title":"使用自定义过滤器的方式实现 Spring Security 的 CORS 跨域配置","time":"2020年10月18日 » "},{"title":"微信小程序云开发登录流程","time":"2020年10月15日 » "},{"title":"微信小程序的userInfoReadyCallback相关解释","time":"2020年10月15日 » "},{"title":"大前端学习路线（详解）","time":"2020年10月13日 » "},{"title":"JavaScript进阶【1-5】JavaScript深入之4类常见内存泄漏及如何避免","time":"2020年10月13日 » "},{"title":"JavaScript进阶【1-4】JavaScript深入之带你走进内存机制","time":"2020年10月13日 » "},{"title":"JavaScript进阶【1-3】JavaScript深入之内存空间详细图解","time":"2020年10月13日 » "},{"title":"配置.editorconfig文件统一开发风格","time":"2020年10月13日 » "},{"title":"ES6处理异步问题的方法：async和await","time":"2020年10月13日 » "},{"title":"通过JavaScript实现设备尺寸的自适应","time":"2020年10月13日 » "},{"title":"JavaScript进阶【1-2】JavaScript深入之执行上下文栈和变量对象","time":"2020年10月13日 » "},{"title":"JavaScript进阶【1-1】理解JavaScript 中的执行上下文和执行栈","time":"2020年10月13日 » "},{"title":">>点击查看更多文章...","time":""}],"1604911570909":[{"title":"TypeScript学习笔记","time":"2020年11月05日 » "},{"title":"计算机组成原理","time":"2020年11月02日 » "},{"title":"React学习记录","time":"2020年11月01日 » "},{"title":"使用自定义过滤器的方式实现 Spring Security 的 CORS 跨域配置","time":"2020年10月18日 » "},{"title":"微信小程序云开发登录流程","time":"2020年10月15日 » "},{"title":"微信小程序的userInfoReadyCallback相关解释","time":"2020年10月15日 » "},{"title":"大前端学习路线（详解）","time":"2020年10月13日 » "},{"title":"JavaScript进阶【1-5】JavaScript深入之4类常见内存泄漏及如何避免","time":"2020年10月13日 » "},{"title":"JavaScript进阶【1-4】JavaScript深入之带你走进内存机制","time":"2020年10月13日 » "},{"title":"JavaScript进阶【1-3】JavaScript深入之内存空间详细图解","time":"2020年10月13日 » "},{"title":"配置.editorconfig文件统一开发风格","time":"2020年10月13日 » "},{"title":"ES6处理异步问题的方法：async和await","time":"2020年10月13日 » "},{"title":"通过JavaScript实现设备尺寸的自适应","time":"2020年10月13日 » "},{"title":"JavaScript进阶【1-2】JavaScript深入之执行上下文栈和变量对象","time":"2020年10月13日 » "},{"title":"JavaScript进阶【1-1】理解JavaScript 中的执行上下文和执行栈","time":"2020年10月13日 » "},{"title":">>点击查看更多文章...","time":""}],"1604911571846":[{"title":"TypeScript学习笔记","time":"2020年11月05日 » "},{"title":"计算机组成原理","time":"2020年11月02日 » "},{"title":"React学习记录","time":"2020年11月01日 » "},{"title":"使用自定义过滤器的方式实现 Spring Security 的 CORS 跨域配置","time":"2020年10月18日 » "},{"title":"微信小程序云开发登录流程","time":"2020年10月15日 » "},{"title":"微信小程序的userInfoReadyCallback相关解释","time":"2020年10月15日 » "},{"title":"大前端学习路线（详解）","time":"2020年10月13日 » "},{"title":"JavaScript进阶【1-5】JavaScript深入之4类常见内存泄漏及如何避免","time":"2020年10月13日 » "},{"title":"JavaScript进阶【1-4】JavaScript深入之带你走进内存机制","time":"2020年10月13日 » "},{"title":"JavaScript进阶【1-3】JavaScript深入之内存空间详细图解","time":"2020年10月13日 » "},{"title":"配置.editorconfig文件统一开发风格","time":"2020年10月13日 » "},{"title":"ES6处理异步问题的方法：async和await","time":"2020年10月13日 » "},{"title":"通过JavaScript实现设备尺寸的自适应","time":"2020年10月13日 » "},{"title":"JavaScript进阶【1-2】JavaScript深入之执行上下文栈和变量对象","time":"2020年10月13日 » "},{"title":"JavaScript进阶【1-1】理解JavaScript 中的执行上下文和执行栈","time":"2020年10月13日 » "},{"title":">>点击查看更多文章...","time":""}],"1604911591201":[{"title":"TypeScript学习笔记","time":"2020年11月05日 » "},{"title":"计算机组成原理","time":"2020年11月02日 » "},{"title":"React学习记录","time":"2020年11月01日 » "},{"title":"使用自定义过滤器的方式实现 Spring Security 的 CORS 跨域配置","time":"2020年10月18日 » "},{"title":"微信小程序云开发登录流程","time":"2020年10月15日 » "},{"title":"微信小程序的userInfoReadyCallback相关解释","time":"2020年10月15日 » "},{"title":"大前端学习路线（详解）","time":"2020年10月13日 » "},{"title":"JavaScript进阶【1-5】JavaScript深入之4类常见内存泄漏及如何避免","time":"2020年10月13日 » "},{"title":"JavaScript进阶【1-4】JavaScript深入之带你走进内存机制","time":"2020年10月13日 » "},{"title":"JavaScript进阶【1-3】JavaScript深入之内存空间详细图解","time":"2020年10月13日 » "},{"title":"配置.editorconfig文件统一开发风格","time":"2020年10月13日 » "},{"title":"ES6处理异步问题的方法：async和await","time":"2020年10月13日 » "},{"title":"通过JavaScript实现设备尺寸的自适应","time":"2020年10月13日 » "},{"title":"JavaScript进阶【1-2】JavaScript深入之执行上下文栈和变量对象","time":"2020年10月13日 » "},{"title":"JavaScript进阶【1-1】理解JavaScript 中的执行上下文和执行栈","time":"2020年10月13日 » "},{"title":">>点击查看更多文章...","time":""}],"1604911606743":[{"title":"TypeScript学习笔记","time":"2020年11月05日 » "},{"title":"计算机组成原理","time":"2020年11月02日 » "},{"title":"React学习记录","time":"2020年11月01日 » "},{"title":"使用自定义过滤器的方式实现 Spring Security 的 CORS 跨域配置","time":"2020年10月18日 » "},{"title":"微信小程序云开发登录流程","time":"2020年10月15日 » "},{"title":"微信小程序的userInfoReadyCallback相关解释","time":"2020年10月15日 » "},{"title":"大前端学习路线（详解）","time":"2020年10月13日 » "},{"title":"JavaScript进阶【1-5】JavaScript深入之4类常见内存泄漏及如何避免","time":"2020年10月13日 » "},{"title":"JavaScript进阶【1-4】JavaScript深入之带你走进内存机制","time":"2020年10月13日 » "},{"title":"JavaScript进阶【1-3】JavaScript深入之内存空间详细图解","time":"2020年10月13日 » "},{"title":"配置.editorconfig文件统一开发风格","time":"2020年10月13日 » "},{"title":"ES6处理异步问题的方法：async和await","time":"2020年10月13日 » "},{"title":"通过JavaScript实现设备尺寸的自适应","time":"2020年10月13日 » "},{"title":"JavaScript进阶【1-2】JavaScript深入之执行上下文栈和变量对象","time":"2020年10月13日 » "},{"title":"JavaScript进阶【1-1】理解JavaScript 中的执行上下文和执行栈","time":"2020年10月13日 » "},{"title":">>点击查看更多文章...","time":""}]}